illogical/__init__.py
illogical/evaluable.py
illogical/illogical.py
illogical-1.0.2.dist-info/LICENSE.md
illogical-1.0.2.dist-info/METADATA
illogical-1.0.2.dist-info/WHEEL
illogical-1.0.2.dist-info/top_level.txt
illogical-1.0.2.dist-info/RECORD
