Metadata-Version: 2.1
Name: illogical
Version: 1.0.2
Summary: A micro conditional engine used to parse raw logical and comparison expressions, evaluate the expression in the given data context, and provide access to a text form of the given expressions.
Author-email: David Horak <info@davidhorak.com>
License: Copyright (c) 2023, David Horak (info@davidhorak.com)
Project-URL: repository, https://github.com/spaceavocado/pyillogical
Keywords: expression,logical,expression-evaluator
Classifier: Development Status :: 5 - Production/Stable
Classifier: Topic :: Utilities
Classifier: Programming Language :: Python
Classifier: Programming Language :: Python :: 3
Classifier: License :: OSI Approved :: MIT License
Requires-Python: >=3.7
License-File: LICENSE.md
